transcrypt/__main__.py
transcrypt/favicon.ico
transcrypt/license_reference.txt
transcrypt/ts
transcrypt/ts.bat
transcrypt/ts_travis
transcrypt/demos/cyclejs_demo/README.md
transcrypt/demos/cyclejs_demo/cyclejs_demo.html
transcrypt/demos/cyclejs_demo/cyclejs_demo.py
transcrypt/demos/cyclejs_demo/cyclejs_http_demo.html
transcrypt/demos/cyclejs_demo/cyclejs_http_demo.py
transcrypt/demos/cyclejs_demo/__target__/cyclejs_http_demo.js
transcrypt/demos/cyclejs_demo/__target__/cyclejs_http_demo.map
transcrypt/demos/cyclejs_demo/__target__/cyclejs_http_demo.project
transcrypt/demos/cyclejs_demo/__target__/cyclejs_http_demo.py
transcrypt/demos/cyclejs_demo/__target__/org.transcrypt.__runtime__.js
transcrypt/demos/cyclejs_demo/__target__/org.transcrypt.__runtime__.map
transcrypt/demos/cyclejs_demo/__target__/org.transcrypt.__runtime__.py
transcrypt/demos/cyclejs_demo/component_demos/isolated_bmi_slider/bmi.html
transcrypt/demos/cyclejs_demo/component_demos/isolated_bmi_slider/bmi.py
transcrypt/demos/cyclejs_demo/component_demos/isolated_bmi_slider/__target__/bmi.js
transcrypt/demos/cyclejs_demo/component_demos/isolated_bmi_slider/__target__/bmi.map
transcrypt/demos/cyclejs_demo/component_demos/isolated_bmi_slider/__target__/bmi.project
transcrypt/demos/cyclejs_demo/component_demos/isolated_bmi_slider/__target__/bmi.py
transcrypt/demos/cyclejs_demo/component_demos/isolated_bmi_slider/__target__/components.labeled_slider.js
transcrypt/demos/cyclejs_demo/component_demos/isolated_bmi_slider/__target__/components.labeled_slider.map
transcrypt/demos/cyclejs_demo/component_demos/isolated_bmi_slider/__target__/components.labeled_slider.py
transcrypt/demos/cyclejs_demo/component_demos/isolated_bmi_slider/__target__/components.snabbdom.js
transcrypt/demos/cyclejs_demo/component_demos/isolated_bmi_slider/__target__/components.snabbdom.map
transcrypt/demos/cyclejs_demo/component_demos/isolated_bmi_slider/__target__/components.snabbdom.py
transcrypt-3.9.4.dist-info/METADATA
transcrypt-3.9.4.dist-info/WHEEL
transcrypt-3.9.4.dist-info/entry_points.txt
transcrypt-3.9.4.dist-info/top_level.txt
transcrypt-3.9.4.dist-info/RECORD
