Metadata-Version: 2.4
Name: Transcrypt
Version: 3.9.4
Summary: Python to JavaScript transpiler, supporting multiple inheritance and generating lean, highly readable code
Home-page: https://www.transcrypt.org
Author: Jacques de Hooge
Author-email: info@transcrypt.org
License: Apache 2.0
Keywords: python,javascript,transpiler,compiler,browser,web,multiple inheritance,transcrypt,django,flask,react
Classifier: Development Status :: 5 - Production/Stable
Classifier: Intended Audience :: Developers
Classifier: Natural Language :: English
Classifier: License :: OSI Approved :: Apache Software License
Classifier: Topic :: Software Development :: Libraries :: Python Modules
Classifier: Operating System :: OS Independent
Classifier: Programming Language :: Python :: 3.9
Requires-Dist: mypy
Dynamic: author
Dynamic: author-email
Dynamic: classifier
Dynamic: description
Dynamic: description-content-type
Dynamic: home-page
Dynamic: keywords
Dynamic: license
Dynamic: requires-dist
Dynamic: summary
